multicaps/__init__.py
multicaps/__version__.py
multicaps/_solver.py
multicaps/_solver_async.py
multicaps/captcha.py
multicaps/common.py
multicaps/exceptions.py
multicaps/proxy.py
multicaps/_captcha/__init__.py
multicaps/_captcha/base.py
multicaps/_captcha/capy.py
multicaps/_captcha/funcaptcha.py
multicaps/_captcha/geetest.py
multicaps/_captcha/geetest_v4.py
multicaps/_captcha/hcaptcha.py
multicaps/_captcha/image.py
multicaps/_captcha/keycaptcha.py
multicaps/_captcha/recaptcha_v2.py
multicaps/_captcha/recaptcha_v3.py
multicaps/_captcha/text.py
multicaps/_captcha/tiktok.py
multicaps/_misc/__init__.py
multicaps/_misc/proxy.py
multicaps/_service/__init__.py
multicaps/_service/anti_captcha.py
multicaps/_service/azcaptcha.py
multicaps/_service/base.py
multicaps/_service/captcha_guru.py
multicaps/_service/cptch_net.py
multicaps/_service/deathbycaptcha.py
multicaps/_service/rucaptcha.py
multicaps/_service/twocaptcha.py
multicaps/_transport/__init__.py
multicaps/_transport/base.py
multicaps/_transport/http_transport.py
multicaps-0.1.1.dist-info/METADATA
multicaps-0.1.1.dist-info/WHEEL
multicaps-0.1.1.dist-info/licenses/LICENSE
multicaps-0.1.1.dist-info/RECORD
