Metadata-Version: 2.4
Name: multicaps
Version: 0.1.1
Summary: Universal CAPTCHA Solver for humans
License-File: LICENSE
Requires-Python: >=3.9
Requires-Dist: httpx>=0.28.1
